qhash/__init__.py
qhash/version.py
qhash/clients/__init__.py
qhash/clients/assistant.py
qhash/clients/call.py
qhash/clients/endpoint.py
qhash/clients/invoke.py
qhash/clients/protos/assistant_analysis_pb2.py
qhash/clients/protos/assistant_analysis_pb2.pyi
qhash/clients/protos/assistant_analysis_pb2_grpc.py
qhash/clients/protos/assistant_api_pb2.py
qhash/clients/protos/assistant_api_pb2.pyi
qhash/clients/protos/assistant_api_pb2_grpc.py
qhash/clients/protos/assistant_deployment_pb2.py
qhash/clients/protos/assistant_deployment_pb2.pyi
qhash/clients/protos/assistant_deployment_pb2_grpc.py
qhash/clients/protos/assistant_knowledge_pb2.py
qhash/clients/protos/assistant_knowledge_pb2.pyi
qhash/clients/protos/assistant_knowledge_pb2_grpc.py
qhash/clients/protos/assistant_tool_pb2.py
qhash/clients/protos/assistant_tool_pb2.pyi
qhash/clients/protos/assistant_tool_pb2_grpc.py
qhash/clients/protos/assistant_webhook_pb2.py
qhash/clients/protos/assistant_webhook_pb2.pyi
qhash/clients/protos/assistant_webhook_pb2_grpc.py
qhash/clients/protos/audit_logging_api_pb2.py
qhash/clients/protos/audit_logging_api_pb2.pyi
qhash/clients/protos/audit_logging_api_pb2_grpc.py
qhash/clients/protos/common_pb2.py
qhash/clients/protos/common_pb2.pyi
qhash/clients/protos/common_pb2_grpc.py
qhash/clients/protos/connect_api_pb2.py
qhash/clients/protos/connect_api_pb2.pyi
qhash/clients/protos/connect_api_pb2_grpc.py
qhash/clients/protos/document_api_pb2.py
qhash/clients/protos/document_api_pb2.pyi
qhash/clients/protos/document_api_pb2_grpc.py
qhash/clients/protos/endpoint_api_pb2.py
qhash/clients/protos/endpoint_api_pb2.pyi
qhash/clients/protos/endpoint_api_pb2_grpc.py
qhash/clients/protos/integration_api_pb2.py
qhash/clients/protos/integration_api_pb2.pyi
qhash/clients/protos/integration_api_pb2_grpc.py
qhash/clients/protos/invoker_api_pb2.py
qhash/clients/protos/invoker_api_pb2.pyi
qhash/clients/protos/invoker_api_pb2_grpc.py
qhash/clients/protos/knowledge_api_pb2.py
qhash_python-0.1.16.dist-info/METADATA
qhash_python-0.1.16.dist-info/WHEEL
qhash_python-0.1.16.dist-info/top_level.txt
qhash_python-0.1.16.dist-info/RECORD
