Metadata-Version: 2.4
Name: qhash-python
Version: 0.1.16
Summary: QhashAI SDK to integrate quantumhash.me APIs
Author-email: Quantumhash_Corporation <admin@quantumhash.me>
License-Expression: MIT
Project-URL: Homepage, https://github.com/Quantumhash-Corporation/qhash-python
Project-URL: Bug Reports, https://github.com/Quantumhash-Corporation/qhash-python/issues
Project-URL: Documentation, https://github.com/Quantumhash-Corporation/qhash-python/blob/main/README.md
Project-URL: Source, https://github.com/Quantumhash-Corporation/qhash-python
Classifier: Development Status :: 5 - Production/Stable
Classifier: Intended Audience :: Developers
Classifier: Operating System :: OS Independent
Classifier: Programming Language :: Python
Classifier: Programming Language :: Python :: 3
Classifier: Programming Language :: Python :: 3.9
Classifier: Programming Language :: Python :: 3.10
Classifier: Programming Language :: Python :: 3.11
Classifier: Topic :: Software Development :: Libraries :: Python Modules
Requires-Python: >=3.9
Requires-Dist: protobuf
Requires-Dist: grpcio
Requires-Dist: grpcio-tools
Provides-Extra: dev
Requires-Dist: pytest; extra == "dev"
Requires-Dist: pytest-cov; extra == "dev"
Requires-Dist: flake8; extra == "dev"
Requires-Dist: black; extra == "dev"
Requires-Dist: mypy; extra == "dev"
